Metadata-Version: 2.1
Name: coutils
Version: 0.1.2
Summary: common code for utils
Home-page: https://github.com/equinoxfitness/datacoco.utils
Author: Paul Singman
Author-email: paul.singman@equinox.com
License: MIT
Download-URL: https://github.com/equinoxfitness/datacoco.util/archive/0.1.tar.gz
Keywords: email tools,ftp tools
Platform: UNKNOWN
